Metadata-Version: 2.1
Name: udak_probability
Version: 0.1
Summary: Gaussian and Binomial distributions
Author: Alan Kang
Author-email: kangfucius@gmail.com
